clio_manage_api_client-0.1.5.dist-info/licenses/LICENSE
clio_manage_python_client/__init__.py
clio_manage_python_client/client.py
clio_manage_python_client/configs.py
clio_manage_python_client/update.py
clio_manage_python_client/classes/__init__.py
clio_manage_python_client/classes/base.py
clio_manage_python_client/classes/requests.py
clio_manage_python_client/classes/responses.py
clio_manage_python_client/db/__init__.py
clio_manage_python_client/db/db_generator.py
clio_manage_python_client/db/response_handler.py
clio_manage_python_client/models/__init__.py
clio_manage_python_client/models/components.py
clio_manage_python_client/models/endpoints.py
clio_manage_python_client/models/fields.py
clio_manage_python_client/models/method_hints.pyi
clio_manage_python_client/models/models_registry.py
clio_manage_python_client/models/query.py
clio_manage_python_client/models/request_body.py
clio_manage_python_client/utils/__init__.py
clio_manage_python_client/utils/export.py
clio_manage_python_client/utils/rate_monitor.py
clio_manage_python_client/utils/time.py
clio_manage_python_client/utils/validate_fields.py
clio_manage_api_client-0.1.5.dist-info/METADATA
clio_manage_api_client-0.1.5.dist-info/WHEEL
clio_manage_api_client-0.1.5.dist-info/top_level.txt
clio_manage_api_client-0.1.5.dist-info/RECORD
