Metadata-Version: 2.4
Name: clio-manage-api-client
Version: 0.1.5
Summary: Python Client for the Clio Manage API.
Home-page: https://github.com/unigrated-solutions/clio-api-python-client
Author: Unigrated Partners
Author-email: dev@unigratedpartners.com
License: Apache-2.0
Project-URL: Bug Tracker, https://github.com/unigrated-solutions/clio-api-python-client/issues
Keywords: clio python client,clio api client,clio manage api,legal,client,sdk,integration,unigration
Classifier: Programming Language :: Python :: 3
Classifier: License :: OSI Approved :: Apache Software License
Classifier: Operating System :: OS Independent
Requires-Python: >=3.8
License-File: LICENSE
Requires-Dist: certifi
Requires-Dist: charset-normalizer
Requires-Dist: et_xmlfile
Requires-Dist: idna
Requires-Dist: mypy-extensions
Requires-Dist: numpy<2.0
Requires-Dist: openpyxl
Requires-Dist: pandas
Requires-Dist: python-dateutil
Requires-Dist: pytz
Requires-Dist: requests
Requires-Dist: six
Requires-Dist: typing-inspect
Requires-Dist: typing_extensions
Requires-Dist: tzdata
Requires-Dist: urllib3
Requires-Dist: aiohttp
Requires-Dist: pyyaml
Requires-Dist: clio-api-model-generator>=0.2.2
Dynamic: author
Dynamic: author-email
Dynamic: classifier
Dynamic: description
Dynamic: description-content-type
Dynamic: home-page
Dynamic: keywords
Dynamic: license
Dynamic: license-file
Dynamic: project-url
Dynamic: requires-dist
Dynamic: requires-python
Dynamic: summary
